<?xml version="1.0" ?>

<container xmlns="http://symfony.com/schema/dic/services"
           xmlns:xsi="http://www.w3.org/2001/XMLSchema-instance"
           xsi:schemaLocation="http://symfony.com/schema/dic/services http://symfony.com/schema/dic/services/services-1.0.xsd">

    <services>
        <service id="phpmob.registry.image_types" class="PhpMob\MediaBundle\Registry\ImageTypeRegistry">
            <argument>%phpmob.filters%</argument>
        </service>

        <service id="phpmob.filesystem_uploader" class="PhpMob\MediaBundle\Uploader\FileUploader">
            <argument type="service" id="oneup_flysystem.phpmob_filesystem"/>
        </service>

        <service class="PhpMob\MediaBundle\EventListener\UploadFileListener">
            <call method="setContainer">
                <argument type="service" id="service_container"/>
            </call>
            <tag name="doctrine.event_subscriber"/>
        </service>

        <service class="PhpMob\MediaBundle\EventListener\DoctrineEventManagerImageTypeRegistryListener">
            <argument type="service" id="phpmob.registry.image_types"/>
            <tag name="doctrine.event_listener" event="imageTypeRegistry"/>
        </service>

        <service class="PhpMob\MediaBundle\Twig\ImagineExtension">
            <argument type="service" id="liip_imagine.cache.manager"/>
            <argument>%phpmob.imagine.filter%</argument>
            <tag name="twig.extension"/>
        </service>

        <service class="PhpMob\MediaBundle\Imagine\Cache\CacheManager"
                 parent="liip_imagine.cache.manager"
                 decorates="liip_imagine.cache.manager">
            <call method="setContainer">
                <argument type="service" id="service_container" />
            </call>
        </service>

        <service id="phpmob.flysystem.phpcr_adapter" class="League\Flysystem\Phpcr\PhpcrAdapter" public="true">
            <argument type="service" id="doctrine_phpcr.session"/>
            <argument>/media</argument>
        </service>
    </services>
</container>
